CHANGELOG.txt
LICENSE.txt
MANIFEST.in
readme.txt
setup.py
TOPSIS_101816021.egg-info/PKG-INFO
TOPSIS_101816021.egg-info/SOURCES.txt
TOPSIS_101816021.egg-info/dependency_links.txt
TOPSIS_101816021.egg-info/requires.txt
TOPSIS_101816021.egg-info/top_level.txt
topsis/topsis.py