Metadata-Version: 2.1
Name: TOPSIS-101816021
Version: 0.0.1
Summary: A Python package to find TOPSIS for multi-criteria decision analysis method
Home-page: https://github.com/daxter-army/topsis_python_package
Author: Mehul Singh Teya
Author-email: mehulsinghteya@gmail.com
License: MIT
Keywords: topsis,UCS538,TIET
Platform: UNKNOWN
Classifier: Development Status :: 3 - Alpha
Classifier: Intended Audience :: Developers
Classifier: Operating System :: Microsoft :: Windows :: Windows 10
Classifier: License :: OSI Approved :: MIT License
Classifier: Programming Language :: Python :: 3
